MANIFEST.in
README.rst
requirements.txt
setup.cfg
setup.py
baruwa/__init__.py
baruwa/baruwa.wsgi
baruwa/websetup.py
baruwa.egg-info/PKG-INFO
baruwa.egg-info/SOURCES.txt
baruwa.egg-info/dependency_links.txt
baruwa.egg-info/entry_points.txt
baruwa.egg-info/not-zip-safe
baruwa.egg-info/paster_plugins.txt
baruwa.egg-info/requires.txt
baruwa.egg-info/top_level.txt
baruwa/commands/__init__.py
baruwa/commands/buildwhitelist.py
baruwa/commands/cdbdump.py
baruwa/commands/changepassword.py
baruwa/commands/checkpassword.py
baruwa/commands/cleanquarantine.py
baruwa/commands/createadmin.py
baruwa/commands/createcdb.py
baruwa/commands/dbclean.py
baruwa/commands/pdfreport.py
baruwa/commands/pdfreportsng.py
baruwa/commands/quarantinereport.py
baruwa/commands/quarantinereportsng.py
baruwa/commands/queuestats.py
baruwa/commands/topspammers.py
baruwa/commands/updatedelta.py
baruwa/commands/updaterulesets.py
baruwa/commands/updatesarules.py
baruwa/config/__init__.py
baruwa/config/deployment.ini_tmpl
baruwa/config/environment.py
baruwa/config/middleware.py
baruwa/config/routing.py
baruwa/config/sql/admin-functions.sql
baruwa/config/sql/functions.sql
baruwa/config/sql/integration.sql
baruwa/controllers/__init__.py
baruwa/controllers/accounts.py
baruwa/controllers/domains.py
baruwa/controllers/error.py
baruwa/controllers/filemanager.py
baruwa/controllers/lists.py
baruwa/controllers/messages.py
baruwa/controllers/organizations.py
baruwa/controllers/reports.py
baruwa/controllers/settings.py
baruwa/controllers/status.py
baruwa/controllers/utils.py
baruwa/forms/__init__.py
baruwa/forms/accounts.py
baruwa/forms/domains.py
baruwa/forms/lists.py
baruwa/forms/messages.py
baruwa/forms/misc.py
baruwa/forms/organizations.py
baruwa/forms/reports.py
baruwa/forms/settings.py
baruwa/forms/status.py
baruwa/i18n/baruwa.pot
baruwa/i18n/baruwajs.pot
baruwa/i18n/af/LC_MESSAGES/baruwa.po
baruwa/i18n/af/LC_MESSAGES/baruwajs.po
baruwa/i18n/ar/LC_MESSAGES/baruwa.po
baruwa/i18n/ar/LC_MESSAGES/baruwajs.po
baruwa/i18n/bg/LC_MESSAGES/baruwa.po
baruwa/i18n/bg/LC_MESSAGES/baruwajs.po
baruwa/i18n/ca/LC_MESSAGES/baruwa.po
baruwa/i18n/ca/LC_MESSAGES/baruwajs.po
baruwa/i18n/cs/LC_MESSAGES/baruwa.po
baruwa/i18n/cs/LC_MESSAGES/baruwajs.po
